das_trader/__init__.py
das_trader/client.py
das_trader/config_manager.py
das_trader/connection.py
das_trader/connection_resilience.py
das_trader/constants.py
das_trader/enhanced_exceptions.py
das_trader/enhanced_logger.py
das_trader/exceptions.py
das_trader/indicators.py
das_trader/locate_manager.py
das_trader/market_data.py
das_trader/market_scanner.py
das_trader/notifications.py
das_trader/orders.py
das_trader/parsers.py
das_trader/positions.py
das_trader/premarket.py
das_trader/utils.py
das_bridge-1.2.0.dist-info/LICENSE
das_bridge-1.2.0.dist-info/METADATA
das_bridge-1.2.0.dist-info/WHEEL
das_bridge-1.2.0.dist-info/top_level.txt
das_bridge-1.2.0.dist-info/RECORD
