Metadata-Version: 2.1
Name: das-bridge
Version: 1.2.0
Summary: Python client for DAS Trader Pro CMD API
Home-page: https://github.com/jefrnc/das-bridge
Author: DAS Bridge Contributors
Author-email: DAS Bridge Team <info@example.com>
License: MIT
Project-URL: Homepage, https://github.com/jefrnc/das-bridge
Project-URL: Documentation, https://github.com/jefrnc/das-bridge/blob/main/README.md
Project-URL: Repository, https://github.com/jefrnc/das-bridge
Project-URL: Bug Tracker, https://github.com/jefrnc/das-bridge/issues
Classifier: Development Status :: 4 - Beta
Classifier: Intended Audience :: Financial and Insurance Industry
Classifier: License :: OSI Approved :: MIT License
Classifier: Programming Language :: Python :: 3
Classifier: Programming Language :: Python :: 3.8
Classifier: Programming Language :: Python :: 3.9
Classifier: Programming Language :: Python :: 3.10
Classifier: Programming Language :: Python :: 3.11
Classifier: Programming Language :: Python :: 3.12
Classifier: Topic :: Office/Business :: Financial :: Investment
Classifier: Topic :: Software Development :: Libraries :: Python Modules
Requires-Python: >=3.8
License-File: LICENSE
Requires-Dist: asyncio
Requires-Dist: aiofiles
Requires-Dist: python-dotenv
Provides-Extra: analysis
Requires-Dist: numpy; extra == "analysis"
Requires-Dist: pandas; extra == "analysis"
Requires-Dist: matplotlib; extra == "analysis"
Provides-Extra: dev
Requires-Dist: pytest>=7.4.0; extra == "dev"
Requires-Dist: black>=23.7.0; extra == "dev"
Requires-Dist: flake8>=6.1.0; extra == "dev"
Requires-Dist: mypy>=1.5.0; extra == "dev"
Requires-Dist: pre-commit>=3.3.0; extra == "dev"
Provides-Extra: notifications
Requires-Dist: aiohttp; extra == "notifications"
Requires-Dist: aiosmtplib; extra == "notifications"
